mbbank/__init__.py
mbbank/capcha_ocr.py
mbbank/main.py
mbbank/mbasync.py
mbbank/wasm_helper/__init__.py
mbbank/wasm_helper/helper.py
mbbankchecker/__init__.py
mbbankchecker/capcha_ocr.py
mbbankchecker/main.py
mbbankchecker/mbasync.py
mbbankchecker/wasm_helper/__init__.py
mbbankchecker/wasm_helper/helper.py
mbbankchecker-0.2.6.dist-info/licenses/LICENSE.txt
mbbankchecker-0.2.6.dist-info/METADATA
mbbankchecker-0.2.6.dist-info/WHEEL
mbbankchecker-0.2.6.dist-info/top_level.txt
mbbankchecker-0.2.6.dist-info/RECORD
